wxbtool/__init__.py
wxbtool/wxb.py
wxbtool/core/__init__.py
wxbtool/core/callbacks.py
wxbtool/core/config.py
wxbtool/core/context.py
wxbtool/core/decorators.py
wxbtool/core/metrics.py
wxbtool/core/model.py
wxbtool/core/plotter.py
wxbtool/core/registries.py
wxbtool/core/resolution.py
wxbtool/core/setting.py
wxbtool/core/types.py
wxbtool/core/phase/__init__.py
wxbtool/core/phase/eval.py
wxbtool/core/phase/infer.py
wxbtool/core/phase/test.py
wxbtool/core/phase/train.py
wxbtool/data/__init__.py
wxbtool/data/aggregator.py
wxbtool/data/climatology.py
wxbtool/data/constants.py
wxbtool/data/dataset.py
wxbtool/data/download.py
wxbtool/data/dsserver.py
wxbtool/data/path.py
wxbtool/data/variables.py
wxbtool/datagen/__init__.py
wxbtool/datagen/gen_climate.py
wxbtool/datagen/util.py
wxbtool/metrics/__init__.py
wxbtool/metrics/acc.py
wxbtool/metrics/crps.py
wxbtool/metrics/rmse.py
wxbtool/norms/__init__.py
wxbtool/norms/meanstd.py
wxbtool/norms/minmax.py
wxbtool/paradigm/__init__.py
wxbtool/paradigm/base.py
wxbtool/paradigm/gan.py
wxbtool/paradigm/seq2seq.py
wxbtool/phys/__init__.py
wxbtool/phys/cloud.py
wxbtool/phys/constants.py
wxbtool/phys/radiation.py
wxbtool/specs/__init__.py
wxbtool/specs/res5_625/__init__.py
wxbtool/specs/res5_625/t850rasp.py
wxbtool/specs/res5_625/t850recur.py
wxbtool/specs/res5_625/t850weyn.py
wxbtool/specs/res5_625/z500weyn.py
wxbtool/util/__init__.py
wxbtool/util/cmaps.py
wxbtool/util/evaluation.py
wxbtool/util/plot.py
wxbtool/zoo/__init__.py
wxbtool/zoo/res5_625/__init__.py
wxbtool/zoo/res5_625/unet/__init__.py
wxbtool/zoo/res5_625/unet/t850d3bg_rasp.py
wxbtool/zoo/res5_625/unet/t850d3bg_weyn.py
wxbtool/zoo/res5_625/unet/t850d3hg_rasp.py
wxbtool/zoo/res5_625/unet/t850d3hg_weyn.py
wxbtool/zoo/res5_625/unet/t850d3sm_rasp.py
wxbtool/zoo/res5_625/unet/t850d3sm_weyn.py
wxbtool-0.3.4.dist-info/licenses/LICENSE
wxbtool-0.3.4.dist-info/METADATA
wxbtool-0.3.4.dist-info/WHEEL
wxbtool-0.3.4.dist-info/entry_points.txt
wxbtool-0.3.4.dist-info/top_level.txt
wxbtool-0.3.4.dist-info/RECORD
