Metadata-Version: 2.4
Name: wxbtool
Version: 0.3.4
Summary: A toolkit for WeatherBench based on PyTorch
Author-email: Mingli Yuan <mingli.yuan@gmail.com>
License: MIT License
Requires-Python: >=3.10
License-File: LICENSE
Requires-Dist: torch>=2.5.2
Requires-Dist: numpy>=2.1.2
Requires-Dist: netcdf4>=1.7.2
Requires-Dist: toolz>=1.0.0
Requires-Dist: dask>=2024.10.0
Requires-Dist: xarray>=0.21.1
Requires-Dist: opencv-python>=4.10.0.84
Requires-Dist: arrow>=1.3.0
Requires-Dist: python-decouple>=3.8
Requires-Dist: leibniz>=0.2.0
Requires-Dist: flask>=3.0.3
Requires-Dist: msgpack>=1.1.0
Requires-Dist: msgpack-numpy>=0.4.8
Requires-Dist: requests>=2.32.3
Requires-Dist: urllib3<3.0.0,>=2.2.3
Requires-Dist: gunicorn>=23.0.0
Requires-Dist: arghandler>=1.3.1
Requires-Dist: lightning<3.0.0,>=2.6.0
Requires-Dist: requests-unixsocket>=0.3.0
Requires-Dist: cdsapi>=0.7.4
Requires-Dist: cartopy>=0.24.1
Requires-Dist: scipy>=1.14.1
Requires-Dist: pandas>=2.2.2
Requires-Dist: torchmetrics>=1.5.0
Dynamic: license-file
